crtoolbox/__init__.py
crtoolbox/bootstrap.py
crtoolbox/coverage.py
crtoolbox/generate.py
crtoolbox/lib/__init__.py
crtoolbox/lib/boundary.py
crtoolbox/lib/cohens.py
crtoolbox/lib/display.py
crtoolbox/lib/fileio.py
crtoolbox/lib/regression.py
crtoolbox/lib/set_theory.py
crtoolbox/tests/__init__.py
crtoolbox/tests/generate_2d_data.py
crtoolbox/tests/generate_ni_data.py
crtoolbox/tests/mask.nii
sims/SpatialSims_Mmu.py
sims/__init__.py
sims/genCfgs_Mmu.py
sims/join_and_plot_Mmu.py
crtoolbox-0.2.0.dist-info/METADATA
crtoolbox-0.2.0.dist-info/WHEEL
crtoolbox-0.2.0.dist-info/top_level.txt
crtoolbox-0.2.0.dist-info/RECORD
