Metadata-Version: 2.4
Name: crtoolbox
Version: 0.2.0
Summary: The Confidence Regions Toolbox
Home-page: https://github.com/tommaullin/crtoolbox
Author: Tom Maullin
Author-email: TomMaullin@gmail.com
Classifier: Programming Language :: Python :: 3
Classifier: License :: OSI Approved :: MIT License
Classifier: Operating System :: OS Independent
Requires-Python: >=3.6
Requires-Dist: matplotlib
Requires-Dist: numpy
Requires-Dist: pandas
Requires-Dist: nibabel
Requires-Dist: nilearn
Requires-Dist: pyyaml
Requires-Dist: plotly
Requires-Dist: nbformat>=4.2.0
Dynamic: author
Dynamic: author-email
Dynamic: classifier
Dynamic: description
Dynamic: description-content-type
Dynamic: home-page
Dynamic: requires-dist
Dynamic: requires-python
Dynamic: summary
